[
  {
    "url": "https://www.urp.cnr.it/node/34956",
    "data_pubblicazione_bando": "09-10-2025",
    "numero_protocollo": "385552",
    "graduatoria_presente": false,
    "data_pubblicazione_graduatoria": null,
    "estratto": "Tipologia:\nConcorsi e Selezioni\n-\nBandi Pubblici - Mobilità\nProtocollo 385552\ndel  09-10-2025\nAvviso pubblico per l’acquisizione di manifestazioni di interesse, riservato a dipendenti di\npubbliche amministrazioni di cui all’art. 1, comma 2 del D.lgs. 165/2001, disponibili a prestare\nservizio in posizione di comando presso il Consiglio Nazionale delle Ricerche\nAVVISO “01- COMANDO-2025-IFC”\nAllegati\nPagina aggiornata il 10-10-2025 09:10:54\nQuesta pagina ti è stata utile?\nSì\nNo\nSelect one\nIl contenuto della pagina non è chiaro\nLe informazioni sono incomplete",
    "allegati": [
      {
        "titolo": "",
        "link": "",
        "protocollo": null,
        "data": null
      }
    ],
    "tipologia": "comando",
    "codice": "AVVISO “01- COMANDO-2025-IFC”"
  },
  {
    "url": "https://www.urp.cnr.it/node/32693",
    "data_pubblicazione_bando": "28-08-2025",
    "numero_protocollo": "319033",
    "graduatoria_presente": false,
    "data_pubblicazione_graduatoria": null,
    "estratto": "Tipologia:\nConcorsi e Selezioni\n-\nBandi Pubblici - Mobilità\nProtocollo 319033\ndel  28-08-2025\nBANDO DI MOBILITÀ ESTERNA VOLONTARIA, PER TITOLI E COLLOQUIO, AI SENSI\nDELL’ART. 30 D.LGS N. 165/2001, PER LA COPERTURA DI N. 1 POSIZIONE, CON\nCONTRATTO DI LAVORO A TEMPO PIENO E INDETERMINATO PROFILO DI\nFUNZIONARIO DI AMMINISTRAZIONE - V LIVELLO PROFESSIONALE – PRESSO L’\nAREA TERRITORIALE DI RICERCA DI ROMA 1 DEL CONSIGLIO NAZIONALE DELLE\nRICERCHE - MONTELIBRETTI\nBANDO N. 365.197 FA AREA ROMA 1\nAllegati\nPagina aggiornata il 29-08-2025 08:08:06\nQuesta pagina ti è stata utile?\nSì\nNo\nSelect one\nIl contenuto della pagina non è chiaro\nLe informazioni sono incomplete",
    "allegati": [
      {
        "titolo": "",
        "link": "",
        "protocollo": null,
        "data": null
      }
    ],
    "tipologia": "mobilità",
    "codice": "BANDO N. 365.197 FA AREA ROMA 1"
  },
  {
    "url": "https://www.urp.cnr.it/node/30523",
    "data_pubblicazione_bando": "07-07-2025",
    "numero_protocollo": "253102",
    "graduatoria_presente": false,
    "data_pubblicazione_graduatoria": null,
    "estratto": "Tipologia:\nConcorsi e Selezioni\n-\nBandi Pubblici - Mobilità\nProtocollo 253102\ndel  07-07-2025\nBANDO DI MOBILITÀ ESTERNA VOLONTARIA, PER TITOLI E COLLOQUIO, AI SENSI DELL’ART. 30 D.LGS N. 165/2001, PER LA COPERTURA DI N. 1 POSIZIONE, CON CONTRATTO DI LAVORO A TEMPO PIENO E INDETERMINATO PROFILO DI FUNZIONARIO DI AMMINISTRAZIONE - V LIVELLO PROFESSIONALE – PRESSO L’ISTITUTO DI SCIENZE MARINE DEL CONSIGLIO NAZIONALE DELLE RICERCHE – SEDE DI ROMA\nBANDO N. 365.195 FA ISMAR\nAllegati\nCommissione\n- Protocollo 392333\ndel 14-10-2025\nPagina aggiornata il 15-10-2025 09:10:05\nQuesta pagina ti è stata utile?\nSì\nNo\nSelect one\nIl contenuto della pagina non è chiaro\nLe informazioni sono incomplete",
    "allegati": [
      {
        "titolo": "Commissione",
        "link": "https://www.urp.cnr.it/system/files?file=2025-10/365.195-nomina-commissione-e-segretario-Mobilita-CTER_signed.pdf",
        "protocollo": "392333",
        "data": "14-10-2025"
      }
    ],
    "tipologia": "mobilità",
    "codice": "BANDO N. 365.195 FA ISMAR"
  },
  {
    "url": "https://www.urp.cnr.it/node/30525",
    "data_pubblicazione_bando": "07-07-2025",
    "numero_protocollo": "253106",
    "graduatoria_presente": false,
    "data_pubblicazione_graduatoria": null,
    "estratto": "Tipologia:\nConcorsi e Selezioni\n-\nBandi Pubblici - Mobilità\nProtocollo 253106\ndel  07-07-2025\nBANDO DI MOBILITÀ ESTERNA VOLONTARIA, PER TITOLI E COLLOQUIO, AI SENSI DELL’ART. 30 D.LGS N. 165/2001, PER LA COPERTURA DI N. 1 POSIZIONE, CON CONTRATTO DI LAVORO A TEMPO PIENO E INDETERMINATO PROFILO DI COLLABORATORE ENTI DI RICERCA - VI LIVELLO PROFESSIONALE – PRESSO L’UNITA’ PIANIFICAZIONE, PROGRAMMAZIONE E BIBLIOTECA CENTRALE DELLA DIREZIONE CENTRALE SERVIZI ALLA RICERCA – DEL CONSIGLIO NAZIONALE DELLE RICERCHE\nBANDO N. 365.196 CTER UPPBC\nAllegati\nRettifica bando\n- Protocollo 266295\ndel 14-07-2025\nPagina aggiornata il 15-07-2025 09:07:38\nQuesta pagina ti è stata utile?\nSì\nNo\nSelect one\nIl contenuto della pagina non è chiaro\nLe informazioni sono incomplete",
    "allegati": [
      {
        "titolo": "Rettifica bando",
        "link": "https://www.urp.cnr.it/system/files?file=2025-07/Rettifica-Bando-365.196-CTER-UPPBC_signed.pdf",
        "protocollo": "266295",
        "data": "14-07-2025"
      }
    ],
    "tipologia": "mobilità",
    "codice": "BANDO N. 365.196 CTER UPPBC"
  },
  {
    "url": "https://www.urp.cnr.it/node/29157",
    "data_pubblicazione_bando": "11-06-2025",
    "numero_protocollo": "210754",
    "graduatoria_presente": false,
    "data_pubblicazione_graduatoria": null,
    "estratto": "Tipologia:\nConcorsi e Selezioni\n-\nBandi Pubblici - Mobilità\nProtocollo 210754\ndel  11-06-2025\nAvviso pubblico per l’acquisizione di manifestazioni di interesse, riservato a dipendenti di\npubbliche amministrazioni di cui all’art. 1, comma 2 del D.lgs. 165/2001, disponibili a prestare\nservizio in posizione di comando presso il Consiglio Nazionale delle Ricerche\nAVVISO “01- COMANDO-2025 ISSIRFA”\nAllegati\nErrata corrige avviso\n- Protocollo 215674\ndel 16-06-2025\nCommissione\n- Protocollo 270140\ndel 16-07-2025\nProvvedimento approvazione atti nomina idonea\n- Protocollo 282765\ndel 23-07-2025\nPagina aggiornata il 24-07-2025 08:07:22\nQuesta pagina ti è stata utile?\nSì\nNo\nSelect one\nIl contenuto della pagina non è chiaro\nLe informazioni sono incomplete",
    "allegati": [
      {
        "titolo": "Errata corrige avviso",
        "link": "https://www.urp.cnr.it/system/files?file=2025-06/Avviso-01-comando-2025-ISSIRFA-Errata-Corrige_signed.pdf",
        "protocollo": "215674",
        "data": "16-06-2025"
      },
      {
        "titolo": "Commissione",
        "link": "https://www.urp.cnr.it/system/files?file=2025-07/Provvedimento-commissione-AVVISO-01-COMANDO-2025-ISSIRFA_signed.pdf",
        "protocollo": "270140",
        "data": "16-07-2025"
      },
      {
        "titolo": "Provvedimento approvazione atti nomina idonea",
        "link": "https://www.urp.cnr.it/system/files?file=2025-07/Provvedimento-approvazione-atti-nomina-idonea-01-COMANDO-2025-ISSIRFA_signed.pdf",
        "protocollo": "282765",
        "data": "23-07-2025"
      }
    ],
    "tipologia": "comando",
    "codice": "AVVISO “01- COMANDO-2025 ISSIRFA”"
  },
  {
    "url": "https://www.urp.cnr.it/node/25778",
    "data_pubblicazione_bando": "11-04-2025",
    "numero_protocollo": "121175",
    "graduatoria_presente": true,
    "data_pubblicazione_graduatoria": "15-07-2025",
    "estratto": "Tipologia:\nConcorsi e Selezioni\n-\nBandi Pubblici - Mobilità\nProtocollo 121175\ndel  11-04-2025\nAvviso pubblico per l’acquisizione di manifestazioni di interesse, riservato a dipendenti di pubbliche\namministrazioni di cui all’art. 1, comma 2 del D.lgs. 165/2001, disponibili a prestare servizio in\nposizione di comando presso il Consiglio Nazionale delle Ricerche\nAvviso 01-COMANDO-2025-ISM\nAllegati\nCommissione [ANNULLATO]\n- Protocollo 182167\ndel 23-05-2025\nCommissione\n- Protocollo 185427\ndel 26-05-2025\nCriteri di valutazione\n- Protocollo 216230\ndel 16-06-2025\nGraduatoria\n- Protocollo 267333\ndel 15-07-2025\nPagina aggiornata il 16-07-2025 08:07:42\nQuesta pagina ti è stata utile?\nSì\nNo\nSelect one\nIl contenuto della pagina non è chiaro\nLe informazioni sono incomplete",
    "allegati": [
      {
        "titolo": "Commissione [ANNULLATO]",
        "link": "https://www.urp.cnr.it/system/files?file=2025-05/Decreto-nomina-Commissione-Comando-001_signed-1.pdf",
        "protocollo": "182167",
        "data": "23-05-2025"
      },
      {
        "titolo": "Commissione",
        "link": "https://www.urp.cnr.it/system/files?file=2025-05/Decreto-nomina-Commissione-Comando-001-cambio_signed.pdf",
        "protocollo": "185427",
        "data": "26-05-2025"
      },
      {
        "titolo": "Criteri di valutazione",
        "link": "https://www.urp.cnr.it/system/files?file=2025-06/Estratto-criteri-di-valutazione-Comando-001_ISM-Oscurato_signed-signed.pdf",
        "protocollo": "216230",
        "data": "16-06-2025"
      },
      {
        "titolo": "Graduatoria",
        "link": "https://www.urp.cnr.it/system/files?file=2025-07/Regolarita-procedimento-e-graduatoria_signed.pdf",
        "protocollo": "267333",
        "data": "15-07-2025"
      }
    ],
    "tipologia": "comando",
    "codice": "Avviso 01-COMANDO-2025-ISM"
  },
  {
    "url": "https://www.urp.cnr.it/node/22882",
    "data_pubblicazione_bando": "07-02-2025",
    "numero_protocollo": "34956",
    "graduatoria_presente": false,
    "data_pubblicazione_graduatoria": null,
    "estratto": "Tipologia:\nConcorsi e Selezioni\n-\nBandi Pubblici - Mobilità\nProtocollo 34956\ndel  07-02-2025\nAvviso pubblico per l’acquisizione di manifestazioni di interesse, riservato a dipendenti di\npubbliche amministrazioni di cui all’art. 1, comma 2 del D.lgs. 165/2001, disponibili a prestare\nservizio in posizione di comando presso il Consiglio Nazionale delle Ricerche AVVISO “01-\nCOMANDO-2025 IREA”\nAvviso 01-COMANDO-2025-IREA\nAllegati\nCommissione\n- Protocollo 107717\ndel 03-04-2025\nSostituzione componente Commissione\n- Protocollo 119110\ndel 10-04-2025\nCriteri di valutazione\n- Protocollo 126992\ndel 15-04-2025\nPagina aggiornata il 16-04-2025 09:04:38\nQuesta pagina ti è stata utile?\nSì\nNo\nSelect one\nIl contenuto della pagina non è chiaro\nLe informazioni sono incomplete",
    "allegati": [
      {
        "titolo": "Commissione",
        "link": "https://www.urp.cnr.it/system/files?file=2025-04/Comando_nomina_Commissione_signed.pdf",
        "protocollo": "107717",
        "data": "03-04-2025"
      },
      {
        "titolo": "Sostituzione componente Commissione",
        "link": "https://www.urp.cnr.it/system/files?file=2025-04/Commissione_comando_sostituzione-Commissario_signed.pdf",
        "protocollo": "119110",
        "data": "10-04-2025"
      },
      {
        "titolo": "Criteri di valutazione",
        "link": "https://www.urp.cnr.it/system/files?file=2025-04/7-STRALCIO-VERBALE-CRITERI_signed.pdf",
        "protocollo": "126992",
        "data": "15-04-2025"
      }
    ],
    "tipologia": "comando",
    "codice": "Avviso 01-COMANDO-2025-IREA"
  },
  {
    "url": "https://www.urp.cnr.it/node/22852",
    "data_pubblicazione_bando": "05-02-2025",
    "numero_protocollo": "32055",
    "graduatoria_presente": false,
    "data_pubblicazione_graduatoria": null,
    "estratto": "Tipologia:\nConcorsi e Selezioni\n-\nBandi Pubblici - Mobilità\nProtocollo 32055\ndel  05-02-2025\nBANDO DI MOBILITÀ ESTERNA VOLONTARIA, PER TITOLI E COLLOQUIO, AI SENSI\nDELL’ART. 30 D.LGS N. 165/2001, PER LA COPERTURA DI N. 1 POSIZIONE, CON\nCONTRATTO DI LAVORO A TEMPO PIENO E INDETERMINATO PROFILO DI\nCOLLABORATORE ENTI DI RICERCA - VI LIVELLO PROFESSIONALE – PRESSO\nL’ISTITUTO DI BIOLOGIA E PATOLOGIA MOLECOLARI (IBPM) – DEL CONSIGLIO\nNAZIONALE DELLE RICERCHE - ROMA\nBANDO N. 365.194 CTER IBPM\nAllegati\nErrata corrige Bando\n- Protocollo 36656\ndel 10-02-2025\nCommissione\n- Protocollo 133239\ndel 18-04-2025\nCriteri di valutazione\n- Protocollo 161323\ndel 12-05-2025\nPagina aggiornata il 13-05-2025 12:05:32\nQuesta pagina ti è stata utile?\nSì\nNo\nSelect one\nIl contenuto della pagina non è chiaro\nLe informazioni sono incomplete",
    "allegati": [
      {
        "titolo": "Errata corrige Bando",
        "link": "https://www.urp.cnr.it/system/files?file=2025-02/Errata-corrige-Bando-365.194-CTER-Ibpm_signed.pdf",
        "protocollo": "36656",
        "data": "10-02-2025"
      },
      {
        "titolo": "Commissione",
        "link": "https://www.urp.cnr.it/system/files?file=2025-04/365.194-nomina-commissione-e-segretario-Mobilita-CTER_signed.pdf",
        "protocollo": "133239",
        "data": "18-04-2025"
      },
      {
        "titolo": "Criteri di valutazione",
        "link": "https://www.urp.cnr.it/system/files?file=2025-05/Bando-365.194-CTER-IBPM-Criteri_Redacted.pdf",
        "protocollo": "161323",
        "data": "12-05-2025"
      }
    ],
    "tipologia": "mobilità",
    "codice": "BANDO N. 365.194 CTER IBPM"
  },
  {
    "url": "https://www.urp.cnr.it/node/22100",
    "data_pubblicazione_bando": "17-12-2024",
    "numero_protocollo": "499875",
    "graduatoria_presente": true,
    "data_pubblicazione_graduatoria": "14-05-2025",
    "estratto": "Tipologia:\nConcorsi e Selezioni\n-\nBandi Pubblici - Mobilità\nProtocollo 499875\ndel  17-12-2024\nBANDO DI MOBILITÀ ESTERNA VOLONTARIA, PER TITOLI E COLLOQUIO, AI SENSI\nDELL’ART. 30 D.LGS N. 165/2001, PER LA COPERTURA DI N. 1 POSIZIONE, CON\nCONTRATTO DI LAVORO A TEMPO PIENO E INDETERMINATO PROFILO DI\nFUNZIONARIO DI AMMINISTRAZIONE - V LIVELLO PROFESSIONALE – PRESSO\nL’ISTITUTO DI SCIENZE DELL’ATMOSFERA E DEL CLIMA DEL CONSIGLIO NAZIONALE\nDELLE RICERCHE - SEDE DI LAMEZIA\nBANDO N. 365.193 FA ISAC\nAllegati\nCommissione\n- Protocollo 68031\ndel 07-03-2025\nCriteri di valutazione\n- Protocollo 108443\ndel 03-04-2025\nGraduatoria\n- Protocollo 165024\ndel 14-05-2025\nPagina aggiornata il 15-05-2025 10:05:40\nQuesta pagina ti è stata utile?\nSì\nNo\nSelect one\nIl contenuto della pagina non è chiaro\nLe informazioni sono incomplete",
    "allegati": [
      {
        "titolo": "Commissione",
        "link": "https://www.urp.cnr.it/system/files?file=2025-03/365.193-Provvedimento-nomina-commissione-e-segretario-Mobilita-Funzionario_signed.pdf",
        "protocollo": "68031",
        "data": "07-03-2025"
      },
      {
        "titolo": "Criteri di valutazione",
        "link": "https://www.urp.cnr.it/system/files?file=2025-04/BANDO-365.193-Modello-per-la-pubblicazione-dei-criteri-signed_signed.pdf",
        "protocollo": "108443",
        "data": "03-04-2025"
      },
      {
        "titolo": "Graduatoria",
        "link": "https://www.urp.cnr.it/system/files?file=2025-05/Bando-365.193-FA-ISAC-Accertamento-e-nomina-vincitore_signed.pdf",
        "protocollo": "165024",
        "data": "14-05-2025"
      }
    ],
    "tipologia": "mobilità",
    "codice": "BANDO N. 365.193 FA ISAC"
  },
  {
    "url": "https://www.urp.cnr.it/node/19903",
    "data_pubblicazione_bando": "20-11-2024",
    "numero_protocollo": "448975",
    "graduatoria_presente": false,
    "data_pubblicazione_graduatoria": null,
    "estratto": "Tipologia:\nConcorsi e Selezioni\n-\nBandi Pubblici - Mobilità\nProtocollo 448975\ndel  20-11-2024\nAvviso pubblico per l’acquisizione di manifestazioni di interesse, riservato a dipendenti di pubbliche\namministrazioni di cui all’art. 1, comma 2 del D.lgs. 165/2001, disponibili a prestare servizio in posizione di\ncomando presso il Consiglio Nazionale delle Ricerche\nAVVISO 01-COMANDO-2024 IBB\nAllegati\nCommissione\n- Protocollo 10738\ndel 15-01-2025\nCriteri di valutazione\n- Protocollo 79912\ndel 17-03-2025\nNomina vincitore\n- Protocollo 83865\ndel 19-03-2025\nPagina aggiornata il 25-03-2025 14:03:58\nQuesta pagina ti è stata utile?\nSì\nNo\nSelect one\nIl contenuto della pagina non è chiaro\nLe informazioni sono incomplete",
    "allegati": [
      {
        "titolo": "Commissione",
        "link": "https://www.urp.cnr.it/system/files?file=2025-01/Nomina-Commissione-Comando_signed.pdf",
        "protocollo": "10738",
        "data": "15-01-2025"
      },
      {
        "titolo": "Criteri di valutazione",
        "link": "https://www.urp.cnr.it/system/files?file=2025-03/Criteri_signed.pdf",
        "protocollo": "79912",
        "data": "17-03-2025"
      },
      {
        "titolo": "Nomina vincitore",
        "link": "https://www.urp.cnr.it/system/files?file=2025-03/Nomina-vincitore-avviso-comando_signed.pdf",
        "protocollo": "83865",
        "data": "19-03-2025"
      }
    ],
    "tipologia": "comando",
    "codice": "AVVISO 01-COMANDO-2024 IBB"
  },
  {
    "url": "https://www.urp.cnr.it/node/18219",
    "data_pubblicazione_bando": "30-10-2024",
    "numero_protocollo": "412067",
    "graduatoria_presente": true,
    "data_pubblicazione_graduatoria": "18-04-2025",
    "estratto": "Tipologia:\nConcorsi e Selezioni\n-\nBandi Pubblici - Mobilità\nProtocollo 412067\ndel  30-10-2024\nBANDO DI MOBILITÀ ESTERNA VOLONTARIA, PER TITOLI E COLLOQUIO, AI SENSI\nDELL’ART. 30 D.LGS N. 165/2001, PER LA COPERTURA DI N. 1 POSIZIONE, CON\nCONTRATTO DI LAVORO A TEMPO PIENO E INDETERMINATO PROFILO DI\nCOLLABORATORE ENTI DI RICERCA - VI LIVELLO PROFESSIONALE – PRESSO\nL’AREA TERRITORIALE DI RICERCA DI COSENZA – DEL CONSIGLIO NAZIONALE DELLE\nRICERCHE\nBANDO N. 365.191 CTER ADR CS\nAllegati\nErrata corrige Bando\n- Protocollo 415273\ndel 31-10-2024\nCommissione\n- Protocollo 19100\ndel 23-01-2025\nCriteri di valutazione\n- Protocollo 56952\ndel 27-02-2025\nGraduatoria\n- Protocollo 133289\ndel 18-04-2025\nPagina aggiornata il 18-04-2025 16:04:30\nQuesta pagina ti è stata utile?\nSì\nNo\nSelect one\nIl contenuto della pagina non è chiaro\nLe informazioni sono incomplete",
    "allegati": [
      {
        "titolo": "Errata corrige Bando",
        "link": "https://www.urp.cnr.it/system/files?file=2024-10/Errata-corrige-Bando-365.191-CTER-ADR-CS_signed.pdf",
        "protocollo": "415273",
        "data": "31-10-2024"
      },
      {
        "titolo": "Commissione",
        "link": "https://www.urp.cnr.it/system/files?file=2025-01/365.191-CTER-ATR-CS-nomina-commissione-e-segretario-Mobilita_signed.pdf",
        "protocollo": "19100",
        "data": "23-01-2025"
      },
      {
        "titolo": "Criteri di valutazione",
        "link": "https://www.urp.cnr.it/system/files?file=2025-02/criteri_365-191_Redacted.pdf",
        "protocollo": "56952",
        "data": "27-02-2025"
      },
      {
        "titolo": "Graduatoria",
        "link": "https://www.urp.cnr.it/system/files?file=2025-04/Bando-365.191-CTER-ATR-CS-Accertamento-e-nomina-vincitore_signed.pdf",
        "protocollo": "133289",
        "data": "18-04-2025"
      }
    ],
    "tipologia": "mobilità",
    "codice": "BANDO N. 365.191 CTER ADR CS"
  },
  {
    "url": "https://www.urp.cnr.it/node/18220",
    "data_pubblicazione_bando": "30-10-2024",
    "numero_protocollo": "412070",
    "graduatoria_presente": true,
    "data_pubblicazione_graduatoria": "14-02-2025",
    "estratto": "Tipologia:\nConcorsi e Selezioni\n-\nBandi Pubblici - Mobilità\nProtocollo 412070\ndel  30-10-2024\nBANDO DI MOBILITÀ ESTERNA VOLONTARIA, PER TITOLI E COLLOQUIO, AI SENSI\nDELL’ART. 30 D.LGS N. 165/2001, PER LA COPERTURA DI N. 1 POSIZIONE, CON\nCONTRATTO DI LAVORO A TEMPO PIENO E INDETERMINATO PROFILO DI\nCOLLABORATORE ENTI DI RICERCA - VI LIVELLO PROFESSIONALE – PRESSO\nL’ISTITUTO DI SCIENZA E TECNOLOGIE DELL’INFORMAZIONE “A.FAEDO” DI PISA – DEL\nCONSIGLIO NAZIONALE DELLE RICERCHE\nBANDO N. 365.192 CTER ISTI\nAllegati\nErrata corrige Bando\n- Protocollo 415275\ndel 31-10-2024\nCommissione\n- Protocollo 498899\ndel 16-12-2024\nCriteri di valutazione\n- Protocollo 1930\ndel 07-01-2025\nGraduatoria\n- Protocollo 42468\ndel 14-02-2025\nPagina aggiornata il 17-02-2025 07:02:29\nQuesta pagina ti è stata utile?\nSì\nNo\nSelect one\nIl contenuto della pagina non è chiaro\nLe informazioni sono incomplete",
    "allegati": [
      {
        "titolo": "Errata corrige Bando",
        "link": "https://www.urp.cnr.it/system/files?file=2024-10/Errata-corrige-Bando-365.192-CTER-ISTI_signed.pdf",
        "protocollo": "415275",
        "data": "31-10-2024"
      },
      {
        "titolo": "Commissione",
        "link": "https://www.urp.cnr.it/system/files?file=2024-12/365.192-CTER-ISTI-nomina-commissione-e-segretario-Mobilita_signed.pdf",
        "protocollo": "498899",
        "data": "16-12-2024"
      },
      {
        "titolo": "Criteri di valutazione",
        "link": "https://www.urp.cnr.it/system/files?file=2025-01/Criteri-Di-Valutazione-Bando-365.192-CTER_signed_signed.pdf",
        "protocollo": "1930",
        "data": "07-01-2025"
      },
      {
        "titolo": "Graduatoria",
        "link": "https://www.urp.cnr.it/system/files?file=2025-02/Bando-365.192-CTER-ISTI-Accertamento-e-nomina-vincitore_signed.pdf",
        "protocollo": "42468",
        "data": "14-02-2025"
      }
    ],
    "tipologia": "mobilità",
    "codice": "BANDO N. 365.192 CTER ISTI"
  },
  {
    "url": "https://www.urp.cnr.it/node/16989",
    "data_pubblicazione_bando": "14-10-2024",
    "numero_protocollo": "379748",
    "graduatoria_presente": true,
    "data_pubblicazione_graduatoria": "05-05-2025",
    "estratto": "Tipologia:\nConcorsi e Selezioni\n-\nBandi Pubblici - Mobilità\nProtocollo 379748\ndel  14-10-2024\nBANDO DI MOBILITÀ ESTERNA VOLONTARIA, PER TITOLI E COLLOQUIO, AI SENSI\nDELL’ART. 30 D.LGS N. 165/2001, PER LA COPERTURA DI N. 1 POSIZIONE, CON\nCONTRATTO DI LAVORO A TEMPO PIENO E INDETERMINATO PROFILO DI\nFUNZIONARIO DI AMMINISTRAZIONE - V LIVELLO PROFESSIONALE – PRESSO IL\nCENTRO INTERDIPARTIMENTALE PER L’ETICA E L’INTEGRITA’ NELLA RICERCA DEL\nCONSIGLIO NAZIONALE DELLE RICERCHE - ROMA\nBANDO N. 365.189 FA CID ETHICS\nAllegati\nCommissione\n- Protocollo 19099\ndel 23-01-2025\nCriteri di valutazione\n- Protocollo 72608\ndel 11-03-2025\nGraduatoria\n- Protocollo 149827\ndel 05-05-2025\nPagina aggiornata il 06-05-2025 08:05:55\nQuesta pagina ti è stata utile?\nSì\nNo\nSelect one\nIl contenuto della pagina non è chiaro\nLe informazioni sono incomplete",
    "allegati": [
      {
        "titolo": "Commissione",
        "link": "https://www.urp.cnr.it/system/files?file=2025-01/365.189-nomina-commissione-e-segretario-Mobilita-Funzionario_signed.pdf",
        "protocollo": "19099",
        "data": "23-01-2025"
      },
      {
        "titolo": "Criteri di valutazione",
        "link": "https://www.urp.cnr.it/system/files?file=2025-03/365.189-FA-CID-ETHICS-Stralcio-criteri_signed.pdf",
        "protocollo": "72608",
        "data": "11-03-2025"
      },
      {
        "titolo": "Graduatoria",
        "link": "https://www.urp.cnr.it/system/files?file=2025-05/Bando-365.189-FA-CID-ETHICS-Accertamento-e-nomina-vincitore_signed.pdf",
        "protocollo": "149827",
        "data": "05-05-2025"
      }
    ],
    "tipologia": "mobilità",
    "codice": "BANDO N. 365.189 FA CID ETHICS"
  },
  {
    "url": "https://www.urp.cnr.it/node/16990",
    "data_pubblicazione_bando": "14-10-2024",
    "numero_protocollo": "379753",
    "graduatoria_presente": true,
    "data_pubblicazione_graduatoria": "28-03-2025",
    "estratto": "Tipologia:\nConcorsi e Selezioni\n-\nBandi Pubblici - Mobilità\nProtocollo 379753\ndel  14-10-2024\nBANDO DI MOBILITÀ ESTERNA VOLONTARIA, PER TITOLI E COLLOQUIO, AI SENSI\nDELL’ART. 30 D.LGS N. 165/2001, PER LA COPERTURA DI N. 1 POSIZIONE, CON\nCONTRATTO DI LAVORO A TEMPO PIENO E INDETERMINATO PROFILO DI\nCOLLABORATORE DI AMMINISTRAZIONE - VII LIVELLO PROFESSIONALE – PRESSO\nL’ISTITUTO DI SCIENZE DELL’ATMOSFERA E DEL CLIMA – SEDE DI ROMA TOR\nVERGATA\nBANDO N. 365.190 CA\nAllegati\nCommissione\n- Protocollo 498896\ndel 16-12-2024\nCriteri di valutazione\n- Protocollo 31935\ndel 05-02-2025\nGraduatoria\n- Protocollo 98740\ndel 28-03-2025\nPagina aggiornata il 31-03-2025 10:03:08\nQuesta pagina ti è stata utile?\nSì\nNo\nSelect one\nIl contenuto della pagina non è chiaro\nLe informazioni sono incomplete",
    "allegati": [
      {
        "titolo": "Commissione",
        "link": "https://www.urp.cnr.it/system/files?file=2024-12/365.190-CA-ISAC-nomina-commissione-e-segretario-Mobilita_signed.pdf",
        "protocollo": "498896",
        "data": "16-12-2024"
      },
      {
        "titolo": "Criteri di valutazione",
        "link": "https://www.urp.cnr.it/system/files?file=2025-02/CRITERI-DI-VALUTAZIONE_BANDO-N-365.190-CA-ISAC_Redacted.pdf",
        "protocollo": "31935",
        "data": "05-02-2025"
      },
      {
        "titolo": "Graduatoria",
        "link": "https://www.urp.cnr.it/system/files?file=2025-03/Bando-365.190-CA-ISAC-Accertamento-e-nomina-vincitore_signed.pdf",
        "protocollo": "98740",
        "data": "28-03-2025"
      }
    ],
    "tipologia": "mobilità",
    "codice": "BANDO N. 365.190 CA"
  },
  {
    "url": "https://www.urp.cnr.it/node/13775",
    "data_pubblicazione_bando": "06-09-2024",
    "numero_protocollo": "307374",
    "graduatoria_presente": false,
    "data_pubblicazione_graduatoria": null,
    "estratto": "Tipologia:\nConcorsi e Selezioni\n-\nBandi Pubblici - Mobilità\nProtocollo 307374\ndel  06-09-2024\nAvviso pubblico per l’acquisizione di manifestazioni di interesse, riservato a dipendenti di\npubbliche amministrazioni di cui all’art. 1, comma 2 del D.lgs. 165/2001, disponibili a prestare\nservizio in posizione di comando presso il Consiglio Nazionale delle Ricerche\nAVVISO “01-COMANDO-2024 IAS”\nAllegati\nCommissione\n- Protocollo 438861\ndel 14-11-2024\nCriteri di valutazione\n- Protocollo 450471\ndel 20-11-2024\nPagina aggiornata il 21-11-2024 07:11:37\nQuesta pagina ti è stata utile?\nSì\nNo\nSelect one\nIl contenuto della pagina non è chiaro\nLe informazioni sono incomplete",
    "allegati": [
      {
        "titolo": "Commissione",
        "link": "https://www.urp.cnr.it/system/files?file=2024-11/GE_Nomina-Commissione-Avviso-1-Comando-IAS_signed.pdf",
        "protocollo": "438861",
        "data": "14-11-2024"
      },
      {
        "titolo": "",
        "link": "",
        "protocollo": null,
        "data": null
      },
      {
        "titolo": "Criteri di valutazione",
        "link": "https://www.urp.cnr.it/system/files?file=2024-11/Pubblicazione-criteri_signed_0.pdf",
        "protocollo": "450471",
        "data": "20-11-2024"
      }
    ],
    "tipologia": "comando",
    "codice": "AVVISO “01-COMANDO-2024 IAS”"
  },
  {
    "url": "https://www.urp.cnr.it/node/6448",
    "data_pubblicazione_bando": "22-05-2024",
    "numero_protocollo": "171285",
    "graduatoria_presente": true,
    "data_pubblicazione_graduatoria": "28-11-2024",
    "estratto": "Tipologia:\nConcorsi e Selezioni\n-\nBandi Pubblici - Mobilità\nProtocollo 171285\ndel  22-05-2024\nBANDO DI MOBILITÀ ESTERNA VOLONTARIA, PER TITOLI E COLLOQUIO, AI SENSI\nDELL’ART. 30 D.LGS N. 165/2001, PER LA COPERTURA DI N. 1 POSIZIONE, CON\nCONTRATTO DI LAVORO A TEMPO PIENO E INDETERMINATO PROFILO DI\nCOLLABORATORE TECNICO ENTI DI RICERCA - VI LIVELLO PROFESSIONALE –\nPRESSO L’ISTITUTO DI SCIENZE E TECNOLOGIE DELLA COGNIZIONE DEL CONSIGLIO\nNAZIONALE DELLE RICERCHE – SEDE DI ROMA\nBANDO N. 365.188 CTER ISTC\nAllegati\nRettifica bando\n- Protocollo 245141\ndel 12-07-2024\nNomina commissione e segretario\n- Protocollo 373892\ndel 10-10-2024\nAvviso di convocazione colloquio\n- Protocollo 420934\ndel 04-11-2024\nCriteri di valutazione\n- Protocollo 449418\ndel 20-11-2024\nGraduatoria\n- Protocollo 466085\ndel 28-11-2024\nPagina aggiornata il 12-12-2024 07:12:41\nQuesta pagina ti è stata utile?\nSì\nNo\nSelect one\nIl contenuto della pagina non è chiaro\nLe informazioni sono incomplete",
    "allegati": [
      {
        "titolo": "Rettifica bando",
        "link": "https://www.urp.cnr.it/system/files?file=2024-07/Rettifica-Bando-365.188-CTER-ISTC_signed.pdf",
        "protocollo": "245141",
        "data": "12-07-2024"
      },
      {
        "titolo": "Nomina commissione e segretario",
        "link": "https://www.urp.cnr.it/system/files?file=2024-10/365.188-CTER-ISTC-nomina-commissione-e-segretario-Mobilita-CTER_signed.pdf",
        "protocollo": "373892",
        "data": "10-10-2024"
      },
      {
        "titolo": "Avviso di convocazione colloquio",
        "link": "https://www.urp.cnr.it/system/files?file=2024-11/AVVISO-CONVOCAZIONE-COLLOQUIO-365.188-CTER-ISTC.pdf",
        "protocollo": "420934",
        "data": "04-11-2024"
      },
      {
        "titolo": "Criteri di valutazione",
        "link": "https://www.urp.cnr.it/system/files?file=2024-11/Criteri-pubblicazione-firmato-bando-365.188_Redacted.pdf",
        "protocollo": "449418",
        "data": "20-11-2024"
      },
      {
        "titolo": "Graduatoria",
        "link": "https://www.urp.cnr.it/system/files?file=2024-12/Bando-365.188-CTER-ISTC-Accertamento-e-nomina-vincitore_signed.pdf",
        "protocollo": "466085",
        "data": "28-11-2024"
      }
    ],
    "tipologia": "mobilità",
    "codice": "BANDO N. 365.188 CTER ISTC"
  },
  {
    "url": "https://www.urp.cnr.it/node/3963",
    "data_pubblicazione_bando": "09-04-2024",
    "numero_protocollo": "118197",
    "graduatoria_presente": true,
    "data_pubblicazione_graduatoria": "06-09-2024",
    "estratto": "Tipologia:\nConcorsi e Selezioni\n-\nBandi Pubblici - Mobilità\nProtocollo 118197\ndel  09-04-2024\nBANDO DI MOBILITÀ ESTERNA VOLONTARIA, PER TITOLI E COLLOQUIO, AI SENSI\nDELL’ART. 30 D.LGS N. 165/2001, PER LA COPERTURA DI N. 1 POSIZIONE, CON\nCONTRATTO DI LAVORO A TEMPO PIENO E INDETERMINATO PROFILO DI\nFUNZIONARIO DI AMMINISTRAZIONE - V LIVELLO PROFESSIONALE – PRESSO\nL’ISTITUTO DI FISIOLOGIA CLINICA (PISA) - SCADENZA 9 MAGGIO 2024\nBANDO N. 365.187 FA IFC\nAllegati\nCommissione\n- Protocollo 194544\ndel 07-06-2024\nCriteri di valutazione\n- Protocollo 247334\ndel 15-07-2024\nAvviso convocazione colloquio\n- Protocollo 282466\ndel 05-08-2024\nGraduatoria\n- Protocollo 307862\ndel 06-09-2024\nPagina aggiornata il 10-09-2024 08:09:26\nQuesta pagina ti è stata utile?\nSì\nNo\nSelect one\nIl contenuto della pagina non è chiaro\nLe informazioni sono incomplete",
    "allegati": [
      {
        "titolo": "Commissione",
        "link": "https://www.urp.cnr.it/system/files?file=2024-06/365.187-FA-IFC-nomina-commissione-e-segretario-Mobilita-Funzionario_signed.pdf",
        "protocollo": "194544",
        "data": "07-06-2024"
      },
      {
        "titolo": "Criteri di valutazione",
        "link": "https://www.urp.cnr.it/system/files?file=2024-07/Bando-n-367.187-FA-IFC-Criteri-di-valutazione_Redacted.pdf",
        "protocollo": "247334",
        "data": "15-07-2024"
      },
      {
        "titolo": "Avviso convocazione colloquio",
        "link": "https://www.urp.cnr.it/system/files?file=2024-08/AVVISO-CONVOCAZIONE-COLLOQUIO-365.187-FA-IFC.docx",
        "protocollo": "282466",
        "data": "05-08-2024"
      },
      {
        "titolo": "Graduatoria",
        "link": "https://www.urp.cnr.it/system/files?file=2024-09/Bando-365.187-FA-IFC-Accertamento-e-nomina-vincitore_signed.pdf",
        "protocollo": "307862",
        "data": "06-09-2024"
      }
    ],
    "tipologia": "mobilità",
    "codice": "BANDO N. 365.187 FA IFC"
  },
  {
    "url": "https://www.urp.cnr.it/node/3316",
    "data_pubblicazione_bando": "27-03-2024",
    "numero_protocollo": "103615",
    "graduatoria_presente": false,
    "data_pubblicazione_graduatoria": null,
    "estratto": "Tipologia:\nConcorsi e Selezioni\n-\nBandi Pubblici - Mobilità\nProtocollo 103615\ndel  27-03-2024\nAvviso pubblico per l’acquisizione di manifestazioni di interesse, riservato a dipendenti di\npubbliche amministrazioni di cui all’art. 1, comma 2 del D.lgs. 165/2001, disponibili a prestare\nservizio in posizione di comando presso il Consiglio Nazionale delle Ricerche\nAVVISO “02-COMANDO-2024 DCGR”\nAVVISO “02-COMANDO-2024 DCGR”\nAllegati\nCommissione\n- Protocollo 156110\ndel 10-05-2024\nCriteri\n- Protocollo 321833\ndel 16-09-2024\nPagina aggiornata il 17-09-2024 15:09:33\nQuesta pagina ti è stata utile?\nSì\nNo\nSelect one\nIl contenuto della pagina non è chiaro\nLe informazioni sono incomplete",
    "allegati": [
      {
        "titolo": "Commissione",
        "link": "https://www.urp.cnr.it/system/files?file=2024-05/DCGR%20ProvvedimentoCommissioneComando02%20DCGR_signed.pdf",
        "protocollo": "156110",
        "data": "10-05-2024"
      },
      {
        "titolo": "Criteri",
        "link": "https://www.urp.cnr.it/system/files?file=2024-09/Protocollo-n-321833-del-16.09.2024-PUBBLICAZIONE-CRITERI-BANDO-400.13-1-signed.pdf",
        "protocollo": "321833",
        "data": "16-09-2024"
      }
    ],
    "tipologia": "comando",
    "codice": "AVVISO “02-COMANDO-2024 DCGR”"
  },
  {
    "url": "https://www.urp.cnr.it/node/3175",
    "data_pubblicazione_bando": "25-03-2024",
    "numero_protocollo": "100558",
    "graduatoria_presente": true,
    "data_pubblicazione_graduatoria": "23-09-2024",
    "estratto": "Tipologia:\nConcorsi e Selezioni\n-\nBandi Pubblici - Mobilità\nProtocollo 100558\ndel  25-03-2024\nBANDO DI MOBILITÀ ESTERNA VOLONTARIA, PER TITOLI E COLLOQUIO, AI SENSI DELL’ART. 30 D.LGS N. 165/2001, PER LA COPERTURA DI N. 1 POSIZIONE, CON CONTRATTO DI LAVORO A TEMPO PIENO E INDETERMINATO PROFILO DI COLLABORATORE TECNICO ENTI DI RICERCA - VI LIVELLO PROFESSIONALE – PRESSO L’UNITÀ COMUNICAZIONE DEL CONSIGLIO NAZIONALE DELLE RICERCHE – SEDE DI GENOVA - SCADENZA 24 APRILE 2024\nBANDO N. 365.186 CTER UC\nAllegati\nCommissione\n- Protocollo 194539\ndel 07-06-2024\nCriteri di valutazione\n- Protocollo 241721\ndel 10-07-2024\nGraduatoria\n- Protocollo 334114\ndel 23-09-2024\nPagina aggiornata il 23-09-2024 12:09:14\nQuesta pagina ti è stata utile?\nSì\nNo\nSelect one\nIl contenuto della pagina non è chiaro\nLe informazioni sono incomplete",
    "allegati": [
      {
        "titolo": "Commissione",
        "link": "https://www.urp.cnr.it/system/files?file=2024-06/365.186-CTER-UC-nomina-commissione-e-segretario-Mobilita-CTER_signed.pdf",
        "protocollo": "194539",
        "data": "07-06-2024"
      },
      {
        "titolo": "Criteri di valutazione",
        "link": "https://www.urp.cnr.it/system/files?file=2024-07/365.186CterUC_Criteri_Redacted.pdf",
        "protocollo": "241721",
        "data": "10-07-2024"
      },
      {
        "titolo": "Graduatoria",
        "link": "https://www.urp.cnr.it/system/files?file=2024-09/Bando-365.186-CTER-UC-Accertamento-e-nomina-vincitore_signed.pdf",
        "protocollo": "334114",
        "data": "23-09-2024"
      }
    ],
    "tipologia": "mobilità",
    "codice": "BANDO N. 365.186 CTER UC"
  },
  {
    "url": "https://www.urp.cnr.it/node/892",
    "data_pubblicazione_bando": "25-01-2024",
    "numero_protocollo": "24810",
    "graduatoria_presente": false,
    "data_pubblicazione_graduatoria": null,
    "estratto": "Tipologia:\nConcorsi e Selezioni\n-\nBandi Pubblici - Mobilità\nProtocollo 24810\ndel  25-01-2024\nAvviso pubblico per l’acquisizione di manifestazioni di interesse, riservato a dipendenti di\npubbliche amministrazioni di cui all’art. 1, comma 2 del D.lgs. 165/2001, disponibili a prestare\nservizio in posizione di comando presso il Consiglio Nazionale delle Ricerche\nAVVISO “01-COMANDO-2024 DCGR”\nAVVISO “01-COMANDO-2024 DCGR”\nAllegati\nAllegato n. 1 - manifestazione di interesse\nAllegato n. 2 - Informativa sul trattamento dati personali ai sensi dell'art. 13 del Regolamento UE 679 del 2016\nCommissione\n- Protocollo 91612\ndel 18-03-2024\nPagina aggiornata il 14-11-2024 10:11:56\nQuesta pagina ti è stata utile?\nSì\nNo\nSelect one\nIl contenuto della pagina non è chiaro\nLe informazioni sono incomplete",
    "allegati": [
      {
        "titolo": "Allegato n. 1 - manifestazione di interesse",
        "link": "https://www.urp.cnr.it/system/files?file=2024-01/Avviso%20pubblico%20Comando%20n.%201_2024%20All.1%20.docx",
        "protocollo": null,
        "data": null
      },
      {
        "titolo": "Allegato n. 2 - Informativa sul trattamento dati personali ai sensi dell'art. 13 del Regolamento UE 679 del 2016",
        "link": "https://www.urp.cnr.it/system/files?file=2024-01/Informativa%20sul%20trattamento%20dati%20personali%20ai%20sensi%20dell%27art.%2013%20del%20Regolamento%20UE%20679%20del%202016%20All2.docx",
        "protocollo": null,
        "data": null
      },
      {
        "titolo": "Commissione",
        "link": "https://www.urp.cnr.it/system/files?file=2024-03/DCGR%20ProvvedimentoCommissioneComando01_signed.pdf",
        "protocollo": "91612",
        "data": "18-03-2024"
      }
    ],
    "tipologia": "comando",
    "codice": "AVVISO “01-COMANDO-2024 DCGR”"
  },
  {
    "url": "https://www.urp.cnr.it/node/788",
    "data_pubblicazione_bando": "22-01-2024",
    "numero_protocollo": "18628",
    "graduatoria_presente": true,
    "data_pubblicazione_graduatoria": "06-09-2024",
    "estratto": "Tipologia:\nConcorsi e Selezioni\n-\nBandi Pubblici - Mobilità\nProtocollo 18628\ndel  22-01-2024\nBANDO DI MOBILITÀ ESTERNA VOLONTARIA, PER TITOLI E COLLOQUIO, AI SENSI\nDELL’ART. 30 D.LGS N. 165/2001, PER LA COPERTURA DI N. 1 POSIZIONE, CON\nCONTRATTO DI LAVORO A TEMPO PIENO E INDETERMINATO PROFILO FUNZIONARIO\nDI AMMINISTRAZIONE V LIVELLO PROFESSIONALE – PRESSO L’AMMINISTRAZIONE\nCENTRALE DEL CONSIGLIO NAZIONALE DELLE RICERCHE – ROMA\nBANDO N. 365.185 FA SAC\nAllegati\nNomina commissione e segretario\n- Protocollo 165508\ndel 17-05-2024\nCriteri di valutazione\n- Protocollo 224366\ndel 28-06-2024\nAvviso convocazione colloquio\nGraduatoria\n- Protocollo 307859\ndel 06-09-2024\nPagina aggiornata il 10-09-2024 08:09:40\nQuesta pagina ti è stata utile?\nSì\nNo\nSelect one\nIl contenuto della pagina non è chiaro\nLe informazioni sono incomplete",
    "allegati": [
      {
        "titolo": "Nomina commissione e segretario",
        "link": "https://www.urp.cnr.it/system/files?file=2024-05/365.185%20FA%20nomina%20commissione%20e%20segretario_signed.pdf",
        "protocollo": "165508",
        "data": "17-05-2024"
      },
      {
        "titolo": "Criteri di valutazione",
        "link": "https://www.urp.cnr.it/system/files?file=2024-06/CRITERI-365.185-FA-SAC_Redacted.pdf",
        "protocollo": "224366",
        "data": "28-06-2024"
      },
      {
        "titolo": "Avviso convocazione colloquio",
        "link": "https://www.urp.cnr.it/system/files?file=2024-07/AVVISO-CONVOCAZIONE-COLLOQUIO-365.185-FA-SAC.pdf",
        "protocollo": null,
        "data": null
      },
      {
        "titolo": "Graduatoria",
        "link": "https://www.urp.cnr.it/system/files?file=2024-09/Bando-365.185-FA-SAC-Accertamento-e-nomina-vincitore_signed.pdf",
        "protocollo": "307859",
        "data": "06-09-2024"
      }
    ],
    "tipologia": "mobilità",
    "codice": "BANDO N. 365.185 FA SAC"
  }
]